xlsx_to_dict/__init__.py
xlsx_to_dict/xlsx_to_dict.py
xlsx_to_dict-0.0.3.dist-info/LICENSE
xlsx_to_dict-0.0.3.dist-info/METADATA
xlsx_to_dict-0.0.3.dist-info/WHEEL
xlsx_to_dict-0.0.3.dist-info/top_level.txt
xlsx_to_dict-0.0.3.dist-info/RECORD
